django_cloudflare_push/__init__.py
django_cloudflare_push/middleware.py
django_cloudflare_push-0.2.2.dist-info/LICENSE
django_cloudflare_push-0.2.2.dist-info/METADATA
django_cloudflare_push-0.2.2.dist-info/WHEEL
django_cloudflare_push-0.2.2.dist-info/top_level.txt
django_cloudflare_push-0.2.2.dist-info/RECORD
