Metadata-Version: 2.1
Name: django-cloudflare-push
Version: 0.2.2
Summary: An piece of middleware that tells CloudFlare to HTTP/2 Push static files in a page to the client.
Home-page: https://github.com/skorokithakis/django-cloudflare-push
Author: Stavros Korokithakis
Author-email: hi@stavros.io
License: BSD
Keywords: django,cloudflare,http2,push
Platform: UNKNOWN
License-File: LICENSE
